Leones/Ruleta.py
Leones/__init__.py
Leones/blackjack.py
Leones/casino.py
Leones/higher_lower.py
Leones/suma.py
Leones/tragaperras.py
Leones/variables.py
Leones-0.2.9.dist-info/METADATA
Leones-0.2.9.dist-info/WHEEL
Leones-0.2.9.dist-info/top_level.txt
Leones-0.2.9.dist-info/RECORD
