Metadata-Version: 2.1
Name: Leones
Version: 0.2.9
Summary: This library consists of a casino simulator, in which you can play various casino games such as black jack.
Home-page: https://github.com/unaidemiguel/Casino-Montepinar.git
Author: Grupo F
Author-email: aitor.fernandezderet@alumni.mondragon.edu
Classifier: Programming Language :: Python :: 3
Classifier: License :: OSI Approved :: MIT License
Classifier: Operating System :: OS Independent
Requires-Python: >=3.9
